MANIFEST.in
README.rst
setup.py
django_bfm/__init__.py
django_bfm/forms.py
django_bfm/models.py
django_bfm/settings.py
django_bfm/tests.py
django_bfm/urls.py
django_bfm/utils.py
django_bfm/views.py
django_bfm.egg-info/PKG-INFO
django_bfm.egg-info/SOURCES.txt
django_bfm.egg-info/dependency_links.txt
django_bfm.egg-info/not-zip-safe
django_bfm.egg-info/requires.txt
django_bfm.egg-info/top_level.txt
django_bfm/static/django_bfm/active.png
django_bfm/static/django_bfm/admin.css
django_bfm/static/django_bfm/admin.js
django_bfm/static/django_bfm/application.css
django_bfm/static/django_bfm/application.js
django_bfm/static/django_bfm/iconic_stroke.eot
django_bfm/static/django_bfm/iconic_stroke.otf
django_bfm/static/django_bfm/iconic_stroke.svg
django_bfm/static/django_bfm/iconic_stroke.ttf
django_bfm/static/django_bfm/upload.jquery.js
django_bfm/templates/django_bfm/admin.js
django_bfm/templates/django_bfm/base.html