Metadata-Version: 1.0
Name: django-bfm
Version: 0.6
Summary: Basic Django File Manager with multifile uploads, live file status, and file deleting.
Home-page: https://github.com/simukis/django-bfm
Author: Simonas Kazlauskas
Author-email: simonas@kazlauskas.me
License: Apache
Keywords: django file manager
Platform: UNKNOWN
Classifier: Framework :: Django
Classifier: Environment :: Web Environment
Classifier: Programming Language :: Python
Classifier: Development Status :: 4 - Beta
Classifier: Intended Audience :: Developers
Classifier: Operating System :: OS Independent
Classifier: License :: OSI Approved :: Apache Software License
Classifier: Topic :: Software Development :: Libraries :: Python Modules
